{"skeleton":{"hash":"Zu0bMDE4lysHDEKmjrEuSAH9Tt8","spine":"3.8.99","x":-52.19,"y":-53.33,"width":104.31,"height":106.58,"images":"","audio":""},"bones":[{"name":"root","scaleX":0.1875,"scaleY":0.1875},{"name":"radar","parent":"root","x":54.34,"y":-43.3}],"slots":[{"name":"base","bone":"root","attachment":"base"},{"name":"radar","bone":"radar","attachment":"radar"}],"skins":[{"name":"default","attachments":{"base":{"base":{"x":68.99,"y":-69.23,"width":140,"height":146}},"radar":{"radar":{"x":-74.51,"y":51.8,"width":238,"height":267}}}}],"animations":{"animation":{"bones":{"radar":{"rotate":[{"time":0.8333,"curve":0.25,"c3":0.75},{"time":1.4667,"angle":-12.02,"curve":"stepped"},{"time":2.1333,"angle":-12.02,"curve":0.25,"c3":0.75},{"time":2.6667,"angle":-23.85,"curve":"stepped"},{"time":3.6667,"angle":-23.85,"curve":0.25,"c3":0.75},{"time":4.3333,"angle":7.03,"curve":"stepped"},{"time":6,"angle":7.03,"curve":0.25,"c3":0.75},{"time":6.6,"angle":-12.66,"curve":"stepped"},{"time":7.8333,"angle":-12.66,"curve":0.25,"c3":0.75},{"time":8.4,"angle":11.38,"curve":0.25,"c3":0.75},{"time":8.9667,"curve":"stepped"},{"time":10}]}}}}}